forxpy/__init__.py
forxpy/forxpy.py
forxpy-2.0.0.dist-info/METADATA
forxpy-2.0.0.dist-info/WHEEL
forxpy-2.0.0.dist-info/LICENSE
forxpy-2.0.0.dist-info/RECORD
