Metadata-Version: 2.1
Name: forxpy
Version: 2.0.0
Summary: Package to access daily exchange rates and forex conversion
License: MIT
Author: Group 6
Requires-Python: >=3.9,<4.0
Classifier: License :: OSI Approved :: MIT License
Classifier: Programming Language :: Python :: 3
Classifier: Programming Language :: Python :: 3.9
Classifier: Programming Language :: Python :: 3.10
Classifier: Programming Language :: Python :: 3.11
Requires-Dist: altair (>=4.2.0,<5.0.0)
Requires-Dist: datetime (>=5.0,<6.0)
Requires-Dist: jsonschema (==4.16.0)
Requires-Dist: myst-parser (>=0.18.1,<0.19.0)
Requires-Dist: pandas (>=1.5.3,<2.0.0)
Requires-Dist: python-semantic-release (>=7.33.0,<8.0.0)
